porkbun/__init__.py
porkbun/api.py
porkbun/cli.py
porkbun/config.py
porkbun/commands/__init__.py
porkbun/commands/account.py
porkbun/commands/automation.py
porkbun/commands/batch.py
porkbun/commands/config.py
porkbun/commands/dns.py
porkbun/commands/domains.py
porkbun/commands/email.py
porkbun/commands/monitor.py
porkbun/commands/ssl.py
porkbun/commands/test_cli.py
porkbun/commands/url.py
porkbun/commands/whois.py
porkbun/commands/workflow.py
porkbun/core/__init__.py
porkbun/core/domain.py
porkbun/utils/__init__.py
porkbun/utils/cache.py
porkbun/utils/config.py
porkbun/utils/exceptions.py
porkbun/utils/logging.py
porkbun/utils/security.py
porkbun/utils/validation.py
porkbun_cli-0.3.0.dist-info/LICENSE
porkbun_cli-0.3.0.dist-info/METADATA
porkbun_cli-0.3.0.dist-info/WHEEL
porkbun_cli-0.3.0.dist-info/entry_points.txt
porkbun_cli-0.3.0.dist-info/top_level.txt
porkbun_cli-0.3.0.dist-info/RECORD
