Metadata-Version: 2.2
Name: porkbun-cli
Version: 0.3.0
Summary: A command-line interface for Porkbun domain management
Home-page: https://github.com/ragelink/porkbun-cli
Author: ragelink
Author-email: ragelink@ragelink.com
Classifier: Development Status :: 4 - Beta
Classifier: Environment :: Console
Classifier: Intended Audience :: Developers
Classifier: Intended Audience :: System Administrators
Classifier: License :: OSI Approved :: MIT License
Classifier: Operating System :: OS Independent
Classifier: Programming Language :: Python :: 3
Classifier: Programming Language :: Python :: 3.8
Classifier: Programming Language :: Python :: 3.9
Classifier: Programming Language :: Python :: 3.10
Classifier: Programming Language :: Python :: 3.11
Classifier: Topic :: Internet :: Name Service (DNS)
Classifier: Topic :: System :: Systems Administration
Requires-Python: >=3.8
License-File: LICENSE
Requires-Dist: click>=8.0.0
Requires-Dist: requests>=2.25.0
Requires-Dist: tabulate>=0.8.0
Requires-Dist: pyyaml>=5.4.0
Requires-Dist: colorama>=0.4.4
Requires-Dist: cryptography>=3.4.0
Requires-Dist: jsonschema>=4.0.0
Dynamic: author
Dynamic: author-email
Dynamic: classifier
Dynamic: description
Dynamic: description-content-type
Dynamic: home-page
Dynamic: requires-dist
Dynamic: requires-python
Dynamic: summary
